api/__init__.py
api/batch_executor.py
api/errors.py
api/pagination.py
api/query_optimizer.py
api/shopify_api.py
api/shopify_graphql.py
shopify_mcp_server-0.2.2.dist-info/licenses/LICENSE
shopify_mcp_server-0.2.2.dist-info/METADATA
shopify_mcp_server-0.2.2.dist-info/WHEEL
shopify_mcp_server-0.2.2.dist-info/entry_points.txt
shopify_mcp_server-0.2.2.dist-info/top_level.txt
shopify_mcp_server-0.2.2.dist-info/RECORD
