Metadata-Version: 2.4
Name: shopify-mcp-server
Version: 0.2.2
Summary: A MCP server for Shopify API integration with Claude Desktop
Home-page: https://github.com/mourigenta/shopify-mcp-server
Author: Mourigenta
Classifier: Programming Language :: Python :: 3
Classifier: License :: OSI Approved :: MIT License
Classifier: Operating System :: OS Independent
Requires-Python: >=3.12
License-File: LICENSE
Requires-Dist: mcp>=1.9.0
Requires-Dist: requests
Requires-Dist: pandas
Requires-Dist: matplotlib
Requires-Dist: python-dotenv
Requires-Dist: urllib3
Dynamic: author
Dynamic: classifier
Dynamic: description
Dynamic: description-content-type
Dynamic: home-page
Dynamic: license-file
Dynamic: requires-dist
Dynamic: requires-python
Dynamic: summary
